mirrorball
