Metadata-Version: 1.0
Name: mirrorball
Version: 0.1.9
Summary: A python package to use neural networks to combine the content of an image with the style of another image
Home-page: https://github.com/ParishaKB/mirrorball
Author: Parisha Bhatia, Soham Sharangpani, Shreyansh Bardia, Ujwal Shah,Aniket Modi,Gaurav Ankalagi
Author-email: UNKNOWN
License: MIT
Platform: UNKNOWN
